{".class": "MypyFile", "_fullname": "libqtile.core.loop", "is_partial_stub_package": false, "is_stub": false, "names": {".class": "SymbolTable", "Callable": {".class": "SymbolTableNode", "cross_ref": "typing.Callable", "kind": "Gdef"}, "Dict": {".class": "SymbolTableNode", "cross_ref": "typing.Dict", "kind": "Gdef"}, "LoopContext": {".class": "SymbolTableNode", "kind": "Gdef", "node": {".class": "TypeInfo", "_promote": null, "abstract_attributes": [], "bases": [{".class": "Instance", "args": [{".class": "AnyType", "missing_import_name": null, "source_any": null, "type_of_any": 4}], "type_ref": "typing.AsyncContextManager"}], "declared_metaclass": null, "defn": {".class": "ClassDef", "fullname": "libqtile.core.loop.LoopContext", "name": "LoopContext", "type_vars": []}, "flags": [], "fullname": "libqtile.core.loop.LoopContext", "metaclass_type": "abc.ABCMeta", "metadata": {}, "module_name": "libqtile.core.loop", "mro": ["libqtile.core.loop.LoopContext", "typing.AsyncContextManager", "builtins.object"], "names": {".class": "SymbolTable", "__aenter__": {".class": "SymbolTableNode", "kind": "Mdef", "node": {".class": "FuncDef", "arg_kinds": [0], "arg_names": ["self"], "flags": ["is_coroutine"], "fullname": "libqtile.core.loop.LoopContext.__aenter__", "name": "__aenter__", "type": {".class": "CallableType", "arg_kinds": [0], "arg_names": ["self"], "arg_types": ["libqtile.core.loop.LoopContext"], "bound_args": [], "def_extras": {"first_arg": "self"}, "fallback": "builtins.function", "implicit": false, "is_ellipsis_args": false, "name": "__aenter__ of LoopContext", "ret_type": {".class": "Instance", "args": [{".class": "AnyType", "missing_import_name": null, "source_any": null, "type_of_any": 6}, {".class": "AnyType", "missing_import_name": null, "source_any": null, "type_of_any": 6}, "libqtile.core.loop.LoopContext"], "type_ref": "typing.Coroutine"}, "type_guard": null, "variables": []}}}, "__aexit__": {".class": "SymbolTableNode", "kind": "Mdef", "node": {".class": "FuncDef", "arg_kinds": [0, 2], "arg_names": ["self", "args"], "flags": ["is_coroutine"], "fullname": "libqtile.core.loop.LoopContext.__aexit__", "name": "__aexit__", "type": {".class": "CallableType", "arg_kinds": [0, 2], "arg_names": ["self", "args"], "arg_types": ["libqtile.core.loop.LoopContext", {".class": "AnyType", "missing_import_name": null, "source_any": null, "type_of_any": 1}], "bound_args": [], "def_extras": {"first_arg": "self"}, "fallback": "builtins.function", "implicit": false, "is_ellipsis_args": false, "name": "__aexit__ of LoopContext", "ret_type": {".class": "Instance", "args": [{".class": "AnyType", "missing_import_name": null, "source_any": null, "type_of_any": 6}, {".class": "AnyType", "missing_import_name": null, "source_any": null, "type_of_any": 6}, {".class": "NoneType"}], "type_ref": "typing.Coroutine"}, "type_guard": null, "variables": []}}}, "__init__": {".class": "SymbolTableNode", "kind": "Mdef", "node": {".class": "FuncDef", "arg_kinds": [0, 1], "arg_names": ["self", "signals"], "flags": [], "fullname": "libqtile.core.loop.LoopContext.__init__", "name": "__init__", "type": {".class": "CallableType", "arg_kinds": [0, 1], "arg_names": ["self", "signals"], "arg_types": ["libqtile.core.loop.LoopContext", {".class": "UnionType", "items": [{".class": "Instance", "args": ["signal.Signals", {".class": "CallableType", "arg_kinds": [2, 4], "arg_names": [null, null], "arg_types": [{".class": "AnyType", "missing_import_name": null, "source_any": null, "type_of_any": 4}, {".class": "AnyType", "missing_import_name": null, "source_any": null, "type_of_any": 4}], "bound_args": [], "def_extras": {}, "fallback": "builtins.function", "implicit": false, "is_ellipsis_args": true, "name": null, "ret_type": {".class": "AnyType", "missing_import_name": null, "source_any": null, "type_of_any": 4}, "type_guard": null, "variables": []}], "type_ref": "builtins.dict"}, {".class": "NoneType"}]}], "bound_args": [], "def_extras": {"first_arg": "self"}, "fallback": "builtins.function", "implicit": false, "is_ellipsis_args": false, "name": "__init__ of LoopContext", "ret_type": {".class": "NoneType"}, "type_guard": null, "variables": []}}}, "_cancel_all_tasks": {".class": "SymbolTableNode", "kind": "Mdef", "node": {".class": "FuncDef", "arg_kinds": [0], "arg_names": ["self"], "flags": ["is_coroutine"], "fullname": "libqtile.core.loop.LoopContext._cancel_all_tasks", "name": "_cancel_all_tasks", "type": null}}, "_handle_exception": {".class": "SymbolTableNode", "kind": "Mdef", "node": {".class": "FuncDef", "arg_kinds": [0, 0, 0], "arg_names": ["self", "loop", "context"], "flags": [], "fullname": "libqtile.core.loop.LoopContext._handle_exception", "name": "_handle_exception", "type": {".class": "CallableType", "arg_kinds": [0, 0, 0], "arg_names": ["self", "loop", "context"], "arg_types": ["libqtile.core.loop.LoopContext", "asyncio.events.AbstractEventLoop", {".class": "Instance", "args": [{".class": "AnyType", "missing_import_name": null, "source_any": null, "type_of_any": 4}, {".class": "AnyType", "missing_import_name": null, "source_any": null, "type_of_any": 4}], "type_ref": "builtins.dict"}], "bound_args": [], "def_extras": {"first_arg": "self"}, "fallback": "builtins.function", "implicit": false, "is_ellipsis_args": false, "name": "_handle_exception of LoopContext", "ret_type": {".class": "NoneType"}, "type_guard": null, "variables": []}}}, "_signals": {".class": "SymbolTableNode", "implicit": true, "kind": "Mdef", "node": {".class": "Var", "flags": [], "fullname": "libqtile.core.loop.LoopContext._signals", "name": "_signals", "type": {".class": "Instance", "args": ["signal.Signals", {".class": "CallableType", "arg_kinds": [2, 4], "arg_names": [null, null], "arg_types": [{".class": "AnyType", "missing_import_name": null, "source_any": null, "type_of_any": 4}, {".class": "AnyType", "missing_import_name": null, "source_any": null, "type_of_any": 4}], "bound_args": [], "def_extras": {}, "fallback": "builtins.function", "implicit": false, "is_ellipsis_args": true, "name": null, "ret_type": {".class": "AnyType", "missing_import_name": null, "source_any": null, "type_of_any": 4}, "type_guard": null, "variables": []}], "type_ref": "builtins.dict"}}}, "_stopped": {".class": "SymbolTableNode", "implicit": true, "kind": "Mdef", "node": {".class": "Var", "flags": [], "fullname": "libqtile.core.loop.LoopContext._stopped", "name": "_stopped", "type": "builtins.bool"}}}, "tuple_type": null, "type_vars": [], "typeddict_type": null}}, "Optional": {".class": "SymbolTableNode", "cross_ref": "typing.Optional", "kind": "Gdef"}, "__doc__": {".class": "SymbolTableNode", "kind": "Gdef", "node": {".class": "Var", "flags": ["is_ready"], "fullname": "libqtile.core.loop.__doc__", "name": "__doc__", "type": "builtins.str"}}, "__file__": {".class": "SymbolTableNode", "kind": "Gdef", "node": {".class": "Var", "flags": ["is_ready"], "fullname": "libqtile.core.loop.__file__", "name": "__file__", "type": "builtins.str"}}, "__name__": {".class": "SymbolTableNode", "kind": "Gdef", "node": {".class": "Var", "flags": ["is_ready"], "fullname": "libqtile.core.loop.__name__", "name": "__name__", "type": "builtins.str"}}, "__package__": {".class": "SymbolTableNode", "kind": "Gdef", "node": {".class": "Var", "flags": ["is_ready"], "fullname": "libqtile.core.loop.__package__", "name": "__package__", "type": "builtins.str"}}, "asyncio": {".class": "SymbolTableNode", "cross_ref": "asyncio", "kind": "Gdef"}, "contextlib": {".class": "SymbolTableNode", "cross_ref": "contextlib", "kind": "Gdef"}, "logger": {".class": "SymbolTableNode", "cross_ref": "libqtile.log_utils.logger", "kind": "Gdef"}, "signal": {".class": "SymbolTableNode", "cross_ref": "signal", "kind": "Gdef"}}, "path": "/usr/lib/python3.9/site-packages/libqtile/core/loop.py"}